cugdth/Color.py
cugdth/__init__.py
cugdth/geotiff_utils.py
cugdth-1.1.5.dist-info/METADATA
cugdth-1.1.5.dist-info/WHEEL
cugdth-1.1.5.dist-info/top_level.txt
cugdth-1.1.5.dist-info/RECORD
