Metadata-Version: 2.1
Name: cugdth
Version: 1.1.5
Summary: A Python package for GeoTIFF file handling
Home-page: https://gitee.com/HaixuHe/cugdt
Author: HaixuHe
Author-email: HaixuHe <20161001925@cug.edu.cn>
Project-URL: Repository, https://gitee.com/HaixuHe/cugdt
Keywords: GeoTIFF,GIS,GDAL
Platform: any
Requires-Python: >=3.7
Requires-Dist: numpy
Requires-Dist: GDAL
Requires-Dist: Pillow
